myPackageWithResFailure/__init__.py
myPackageWithResFailure/core.py
myPackageWithResFailure-0.1.0.dist-info/METADATA
myPackageWithResFailure-0.1.0.dist-info/WHEEL
myPackageWithResFailure-0.1.0.dist-info/top_level.txt
myPackageWithResFailure-0.1.0.dist-info/RECORD
